lightweight_gan/__init__.py
lightweight_gan/cli.py
lightweight_gan/diff_augment.py
lightweight_gan/diff_augment_test.py
lightweight_gan/lightweight_gan.py
lightweight_gan/version.py
singtech_lightweight_gan_v1-1.1.1.dist-info/LICENSE
singtech_lightweight_gan_v1-1.1.1.dist-info/METADATA
singtech_lightweight_gan_v1-1.1.1.dist-info/WHEEL
singtech_lightweight_gan_v1-1.1.1.dist-info/entry_points.txt
singtech_lightweight_gan_v1-1.1.1.dist-info/top_level.txt
singtech_lightweight_gan_v1-1.1.1.dist-info/RECORD
